LICENSE.txt
README.md
setup.cfg
setup.py
kfpubsub/__init__.py
kfpubsub/pubSub.py
kfpubsub/utils.py
kfpubsub.egg-info/PKG-INFO
kfpubsub.egg-info/SOURCES.txt
kfpubsub.egg-info/dependency_links.txt
kfpubsub.egg-info/not-zip-safe
kfpubsub.egg-info/requires.txt
kfpubsub.egg-info/top_level.txt