Metadata-Version: 2.1
Name: kfpubsub
Version: 0.3.5
Summary: Base redis pubsub implementation
Home-page: https://gitlab.com/kas-factory/packages/pubsub
Author: Antonio @ KF
Author-email: antonio@kasfactory.net
License: COPYRIGHT
Platform: UNKNOWN
License-File: LICENSE.txt
